talon
tests
