Metadata-Version: 1.0
Name: talon
Version: 1.2.3
Summary: Mailgun library to extract message quotations and signatures.
Home-page: https://github.com/mailgun/talon
Author: Mailgun Inc.
Author-email: admin@mailgunhq.com
License: APACHE2
Platform: UNKNOWN
